prompd/__init__.py
prompd/__main__.py
prompd/cli.py
prompd/compiler.py
prompd/config.py
prompd/dependency_resolver.py
prompd/exceptions.py
prompd/executor.py
prompd/extractors.py
prompd/interactive.py
prompd/mcp_server.py
prompd/models.py
prompd/package_resolver.py
prompd/package_validator.py
prompd/parser.py
prompd/registry.py
prompd/section_override_processor.py
prompd/security.py
prompd/shell.py
prompd/validator.py
prompd/assets/prompts/cli/python/command-planner.prmd
prompd/assets/prompts/cli/python/prompd-assistant.prmd
prompd/commands/__init__.py
prompd/commands/config.py
prompd/commands/create.py
prompd/commands/git_ops.py
prompd/commands/package.py
prompd/commands/provider.py
prompd/commands/registry.py
prompd/commands/version.py
prompd/providers/__init__.py
prompd/providers/anthropic.py
prompd/providers/base.py
prompd/providers/custom.py
prompd/providers/loader.py
prompd/providers/ollama.py
prompd/providers/openai.py
prompd/providers/registry.py
prompd/shell/__init__.py
prompd/shell/assistant.py
prompd/shell/interactive.py
prompd/utils/assets.py
prompd-0.3.4.dist-info/METADATA
prompd-0.3.4.dist-info/WHEEL
prompd-0.3.4.dist-info/entry_points.txt
prompd-0.3.4.dist-info/top_level.txt
prompd-0.3.4.dist-info/RECORD
