Metadata-Version: 2.4
Name: prompd
Version: 0.3.4
Summary: Structured prompt management CLI with universal LLM provider support, version control, and git integration
Author-email: Logikbug <contact@logikbug.com>
Maintainer-email: Logikbug <contact@logikbug.com>
License-Expression: MIT
Project-URL: Homepage, https://github.com/Logikbug/prompd-cli
Project-URL: Repository, https://github.com/Logikbug/prompd-cli
Project-URL: Documentation, https://github.com/Logikbug/prompd-cli/tree/main/docs
Project-URL: Issues, https://github.com/Logikbug/prompd-cli/issues
Keywords: prompt,prompd,prompt-management,prompt-engineering,template,ai,cli,llm,openai,anthropic,ollama,local-llm,groq,together-ai
Classifier: Development Status :: 3 - Alpha
Classifier: Intended Audience :: Developers
Classifier: Intended Audience :: Information Technology
Classifier: Operating System :: OS Independent
Classifier: Programming Language :: Python :: 3
Classifier: Programming Language :: Python :: 3.8
Classifier: Programming Language :: Python :: 3.9
Classifier: Programming Language :: Python :: 3.10
Classifier: Programming Language :: Python :: 3.11
Classifier: Programming Language :: Python :: 3.12
Classifier: Topic :: Scientific/Engineering :: Artificial Intelligence
Classifier: Topic :: Software Development :: Libraries :: Python Modules
Classifier: Topic :: Text Processing :: Markup
Classifier: Topic :: Utilities
Classifier: Environment :: Console
Requires-Python: >=3.8
Requires-Dist: pyyaml>=6.0
Requires-Dist: click>=8.0
Requires-Dist: rich>=13.0
Requires-Dist: jinja2>=3.0
Requires-Dist: jsonschema>=4.0
Requires-Dist: pydantic>=2.0
Requires-Dist: httpx>=0.24.0
Requires-Dist: python-dotenv>=1.0.0
Requires-Dist: cryptography>=41.0.0
Requires-Dist: networkx>=3.0
Requires-Dist: semver>=3.0.0
Requires-Dist: openpyxl>=3.1.0
Requires-Dist: python-docx>=1.1.0
Requires-Dist: PyPDF2>=3.0.0
Requires-Dist: python-pptx>=0.6.23
Requires-Dist: Pillow>=10.0.0
Provides-Extra: dev
Requires-Dist: pytest>=7.0; extra == "dev"
Requires-Dist: pytest-cov>=4.0; extra == "dev"
Requires-Dist: black>=23.0; extra == "dev"
Requires-Dist: ruff>=0.1.0; extra == "dev"
Provides-Extra: mcp
Requires-Dist: fastapi>=0.111.0; extra == "mcp"
Requires-Dist: uvicorn[standard]>=0.30.0; extra == "mcp"
